donzo_plus/__init__.py
donzo_plus/cal_plus.py
donzo_plus-0.1.5.dist-info/METADATA
donzo_plus-0.1.5.dist-info/WHEEL
donzo_plus-0.1.5.dist-info/entry_points.txt
donzo_plus-0.1.5.dist-info/top_level.txt
donzo_plus-0.1.5.dist-info/RECORD
