Metadata-Version: 2.1
Name: donzo_plus
Version: 0.1.5
Summary: Default template for PDM package
Author-email: lsiwh37249 <lsiwh37249@gmail.com>
License: MIT
Requires-Python: >=3.9
